b3dnet/__init__.py
b3dnet/connection.py
b3dnet/request.py
b3dnet-0.0.1.dist-info/LICENSE
b3dnet-0.0.1.dist-info/METADATA
b3dnet-0.0.1.dist-info/WHEEL
b3dnet-0.0.1.dist-info/top_level.txt
b3dnet-0.0.1.dist-info/RECORD
