Metadata-Version: 2.1
Name: b3dnet
Version: 0.0.1
Summary: TCP Requests to communicate with local realtime applications.
Author-email: "D.Hsu - cgtinker" <hello@cgtinker.com>
Maintainer-email: "D.Hsu - cgtinker" <hello@cgtinker.com>
Project-URL: Homepage, https://github.com/cgtinker/TCPRequests
Project-URL: Bug Tracker, https://github.com/cgtinker/TCPRequests/issues
Keywords: tcp,server,local,realtime
Requires-Python: >=3.7
License-File: LICENSE
